Metadata-Version: 2.1
Name: FirestoreExtractor
Version: 1.7
Summary: Extracts data from cloud firestore and firebase database
Home-page: https://github.com/praKhr/FirestoreExtractor
Maintainer: Prakhar Gandhi
Maintainer-email: gprakhar0@gmail.com
License: UNKNOWN
Download-URL: https://github.com/prakHr/FirestoreExtractor-v/archive/refs/tags/v17.tar.gz
Platform: UNKNOWN
License-File: LICENSE.txt
